setup.py
jil/Image.py
jil/__init__.py
jil.egg-info/PKG-INFO
jil.egg-info/SOURCES.txt
jil.egg-info/dependency_links.txt
jil.egg-info/not-zip-safe
jil.egg-info/top_level.txt