Metadata-Version: 1.0
Name: jil
Version: 0.1
Summary: Joe's Imaging Library
Home-page: http://github.com/j3harvey/jil
Author: Joseph Harvey
Author-email: Joseph.Harvey@cruk.cam.ac.uk
License: MIT
Platform: UNKNOWN
